meld/__init__.py
meld/benchmark.py
meld/cluster.py
meld/filter.py
meld/meld.py
meld/utils.py
meld/version.py
meld-1.0.2.dist-info/LICENSE
meld-1.0.2.dist-info/LICENSE-GPL3.txt
meld-1.0.2.dist-info/METADATA
meld-1.0.2.dist-info/WHEEL
meld-1.0.2.dist-info/top_level.txt
meld-1.0.2.dist-info/RECORD
