Metadata-Version: 2.1
Name: meld
Version: 1.0.2
Summary: MELD
Home-page: https://github.com/KrishnaswamyLab/MELD
Download-URL: https://github.com/KrishnaswamyLab/MELD/archive/v1.0.2.tar.gz
Author: Daniel Burkhardt, Krishnaswamy Lab, Yale University
Author-email: daniel.burkhardt@yale.edu
License: Dual License - See LICENSE file
Keywords: big-data,manifold-learning,computational-biology
Classifier: Development Status :: 5 - Production/Stable
Classifier: Intended Audience :: Developers
Classifier: Intended Audience :: Science/Research
Classifier: Natural Language :: English
Classifier: Operating System :: MacOS :: MacOS X
Classifier: Operating System :: Microsoft :: Windows
Classifier: Operating System :: POSIX :: Linux
Classifier: Programming Language :: Python :: 3
Classifier: Programming Language :: Python :: 3.6
Classifier: Programming Language :: Python :: 3.7
Classifier: Programming Language :: Python :: 3.8
Classifier: Topic :: Scientific/Engineering :: Bio-Informatics
Requires-Python: >=3.5
License-File: LICENSE
License-File: LICENSE-GPL3.txt
Requires-Dist: numpy (>=1.14.0)
Requires-Dist: scipy (>=1.1.0)
Requires-Dist: graphtools (>=1.5.0)
Requires-Dist: pandas (>=0.25)
Requires-Dist: scprep (>=1.0)
Requires-Dist: pygsp
Requires-Dist: scikit-learn
Provides-Extra: doc
Requires-Dist: sphinx ; extra == 'doc'
Requires-Dist: sphinxcontrib-napoleon ; extra == 'doc'
Requires-Dist: autodocsumm ; extra == 'doc'
Provides-Extra: test
Requires-Dist: nose ; extra == 'test'
Requires-Dist: nose2 ; extra == 'test'
Requires-Dist: coverage ; extra == 'test'
Requires-Dist: coveralls ; extra == 'test'
Requires-Dist: scikit-learn ; extra == 'test'
Requires-Dist: packaging ; extra == 'test'
Requires-Dist: matplotlib ; extra == 'test'
Requires-Dist: parameterized ; extra == 'test'
Requires-Dist: phate ; extra == 'test'
